garson/__init__.py
garson/_lib/__init__.py
garson/_lib/constants.py
garson/_lib/info.py
garson/_lib/log.py
garson/_lib/utils.py
garson/_lib/validators.py
garson/guards/__init__.py
garson/guards/base.py
garson/hubs/__init__.py
garson/hubs/base.py
garson/impl/__init__.py
garson/ipc/__init__.py
garson/ipc/cells/__init__.py
garson/ipc/cells/base.py
garson/ipc/cells/file.py
garson/ipc/cells/mp.py
garson/rcs/__init__.py
garson/rcs/base.py
garson/rcs/daemon.py
garson/schedulers/__init__.py
garson/schedulers/base.py
garson/schedulers/interval.py
garson/schedulers/helpers/__init__.py
garson/schedulers/helpers/cached.py
garson/schedulers/helpers/manual.py
garson/services/__init__.py
garson/services/base.py
garson/services/interval.py
garson-0.2.2.dist-info/LICENSE
garson-0.2.2.dist-info/METADATA
garson-0.2.2.dist-info/WHEEL
garson-0.2.2.dist-info/top_level.txt
garson-0.2.2.dist-info/RECORD
