Metadata-Version: 2.2
Name: garson
Version: 0.2.2
Summary: The library that serves
Author-email: Dima Burmistrov <pyctrl.dev@gmail.com>
License: Copyright (c) 2023-2025 Dmitry Burmistrov
Project-URL: homepage, https://github.com/pyctrl/garson
Project-URL: issues, https://github.com/pyctrl/garson/issues
Keywords: garson,service
Classifier: Programming Language :: Python :: 3
Classifier: License :: OSI Approved :: MIT License
Classifier: Operating System :: Unix
Classifier: Intended Audience :: Developers
Classifier: Topic :: Software Development :: Libraries :: Python Modules
Requires-Python: >=3.8
License-File: LICENSE
Provides-Extra: rc-daemon
Requires-Dist: python-daemon<4.0.0; extra == "rc-daemon"
Provides-Extra: svc-bjoern
Requires-Dist: bjoern<4.0.0; extra == "svc-bjoern"
Provides-Extra: all
Requires-Dist: garson[rc-daemon,svc-bjoern]; extra == "all"
